.gitignore
.travis.yml
LICENSE
README.md
environment.yml
requirements.txt
setup.py
scripts/__init__.py
scripts/visbeats
visbeats/__init__,py
visbeats/main.py
visbeats.egg-info/PKG-INFO
visbeats.egg-info/SOURCES.txt
visbeats.egg-info/dependency_links.txt
visbeats.egg-info/top_level.txt
visbeats/visbeats/__init__.py
visbeats/visbeats/adefines.py
visbeats/visbeats/afilemanager.py
visbeats/visbeats/afuncdict.py
visbeats/visbeats/aimports.py
visbeats/visbeats/aobject.py
visbeats/visbeats/aparamdict.py
visbeats/visbeats/audio.py
visbeats/visbeats/audioclip.py
visbeats/visbeats/event.py
visbeats/visbeats/eventlist.py
visbeats/visbeats/image.py
visbeats/visbeats/image_cv.py
visbeats/visbeats/mediafiles.py
visbeats/visbeats/sourcelocationparser.py
visbeats/visbeats/timesignal.py
visbeats/visbeats/timesignal1d.py
visbeats/visbeats/vbmidi.py
visbeats/visbeats/vbobject.py
visbeats/visbeats/video.py
visbeats/visbeats/video_cv.py
visbeats/visbeats/videoclip.py
visbeats/visbeats/videosource.py
visbeats/visbeats/visbeatdefines.py
visbeats/visbeats/visbeatexamplevideo.py
visbeats/visbeats/visbeatimports.py
visbeats/visbeats/visualbeat.py
visbeats/visbeats/warp.py
visbeats/visbeats/assets/audio/hit.wav
visbeats/visbeats/assets/images/VisBeatWatermark.png
visbeats/visbeats/fileui/__init__.py
visbeats/visbeats/fileui/uipath.py
visbeats/visbeats/vbgui/__init__.py
visbeats/visbeats/vbgui/beatgui.py