Metadata-Version: 2.1
Name: visbeats
Version: 0.0.3
Summary: A python package making videos dance
Home-page: https://github.com/austinbrown34/visbeats-pip
Author: Austin Brown
Author-email: austinbrown34@gmail.com
Classifier: Programming Language :: Python :: 3
Classifier: Operating System :: OS Independent
Classifier: License :: OSI Approved :: MIT License
License-File: LICENSE
